trustpy/__init__.py
trustpy/__main__.py
trustpy/cond_nts.py
trustpy/nts.py
trustpy_tools-2.0.14.dist-info/licenses/LICENSE
trustpy_tools-2.0.14.dist-info/METADATA
trustpy_tools-2.0.14.dist-info/WHEEL
trustpy_tools-2.0.14.dist-info/entry_points.txt
trustpy_tools-2.0.14.dist-info/top_level.txt
trustpy_tools-2.0.14.dist-info/RECORD
